[
  {
    "code": "301439",
    "name": "泓淋电力",
    "grade": "S",
    "score": 89,
    "reason": "首板龙头，封单比7.2%，强势"
  },
  {
    "code": "600162",
    "name": "香江控股",
    "grade": "S",
    "score": 90,
    "reason": "5连板地产龙头，封单比1.6%"
  },
  {
    "code": "605277",
    "name": "新亚电子",
    "grade": "A",
    "score": 76,
    "reason": "2连板，封单比2.7%"
  },
  {
    "code": "301360",
    "name": "荣旗科技",
    "grade": "A",
    "score": 76,
    "reason": "首板，封单比3.9%"
  },
  {
    "code": "001269",
    "name": "欧晶科技",
    "grade": "A",
    "score": 74,
    "reason": "2连板，封单比2.0%"
  },
  {
    "code": "000037",
    "name": "深南电A",
    "grade": "A",
    "score": 74,
    "reason": "2连板，封单比2.4%"
  },
  {
    "code": "600865",
    "name": "百大集团",
    "grade": "A",
    "score": 74,
    "reason": "2连板，封单比2.0%"
  },
  {
    "code": "002995",
    "name": "天地在线",
    "grade": "A",
    "score": 73,
    "reason": "3连板，封单比1.5%"
  }
]
